Metadata-Version: 2.4
Name: py-evm
Version: 0.12.0b2
Summary: Python implementation of the Ethereum Virtual Machine
Home-page: https://github.com/ethereum/py-evm
Author: Ethereum Foundation
Author-email: snakecharmers@ethereum.org
License: MIT
Keywords: ethereum blockchain evm
Classifier: Development Status :: 3 - Alpha
Classifier: Intended Audience :: Developers
Classifier: License :: OSI Approved :: MIT License
Classifier: Natural Language :: English
Classifier: Programming Language :: Python :: 3
Classifier: Programming Language :: Python :: 3.8
Classifier: Programming Language :: Python :: 3.9
Classifier: Programming Language :: Python :: 3.10
Classifier: Programming Language :: Python :: 3.11
Classifier: Programming Language :: Python :: 3.12
Classifier: Programming Language :: Python :: 3.13
Requires-Python: >=3.8, <4
License-File: LICENSE
Requires-Dist: cached-property>=1.5.1
Requires-Dist: eth-bloom>=1.0.3
Requires-Dist: eth-keys>=0.4.0
Requires-Dist: eth-typing>=5.2.0
Requires-Dist: eth-utils>=2.0.0
Requires-Dist: lru-dict>=1.1.6
Requires-Dist: py-ecc>=8.0.0
Requires-Dist: rlp>=3.0.0
Requires-Dist: trie>=2.0.0
Requires-Dist: ckzg>=2.0.0
Provides-Extra: benchmark
Requires-Dist: termcolor>=1.1.0; extra == "benchmark"
Requires-Dist: web3>=6.0.0; extra == "benchmark"
Provides-Extra: dev
Requires-Dist: build>=0.9.0; extra == "dev"
Requires-Dist: bump_my_version>=0.19.0; extra == "dev"
Requires-Dist: ipython; extra == "dev"
Requires-Dist: mypy==1.10.0; extra == "dev"
Requires-Dist: pre-commit>=3.4.0; extra == "dev"
Requires-Dist: tox>=4.0.0; extra == "dev"
Requires-Dist: twine; extra == "dev"
Requires-Dist: wheel; extra == "dev"
Requires-Dist: py-evm>=0.8.0b1; extra == "dev"
Requires-Dist: sphinx>=6.0.0; extra == "dev"
Requires-Dist: sphinx-autobuild>=2021.3.14; extra == "dev"
Requires-Dist: sphinx_rtd_theme>=1.0.0; extra == "dev"
Requires-Dist: sphinxcontrib-asyncio>=0.2.0; extra == "dev"
Requires-Dist: towncrier<25,>=24; extra == "dev"
Requires-Dist: cached-property>=1.5.1; extra == "dev"
Requires-Dist: eth-bloom>=1.0.3; extra == "dev"
Requires-Dist: eth-keys>=0.4.0; extra == "dev"
Requires-Dist: eth-typing>=5.2.0; extra == "dev"
Requires-Dist: eth-utils>=2.0.0; extra == "dev"
Requires-Dist: lru-dict>=1.1.6; extra == "dev"
Requires-Dist: py-ecc>=8.0.0; extra == "dev"
Requires-Dist: rlp>=3.0.0; extra == "dev"
Requires-Dist: trie>=2.0.0; extra == "dev"
Requires-Dist: ckzg>=2.0.0; extra == "dev"
Requires-Dist: factory-boy>=3.0.0; extra == "dev"
Requires-Dist: hypothesis<7,>=6; extra == "dev"
Requires-Dist: pytest>=7.0.0; extra == "dev"
Requires-Dist: pytest-asyncio>=0.20.0; extra == "dev"
Requires-Dist: pytest-cov>=4.0.0; extra == "dev"
Requires-Dist: pytest-timeout>=2.0.0; extra == "dev"
Requires-Dist: pytest-xdist>=3.0; extra == "dev"
Provides-Extra: docs
Requires-Dist: py-evm>=0.8.0b1; extra == "docs"
Requires-Dist: sphinx>=6.0.0; extra == "docs"
Requires-Dist: sphinx-autobuild>=2021.3.14; extra == "docs"
Requires-Dist: sphinx_rtd_theme>=1.0.0; extra == "docs"
Requires-Dist: sphinxcontrib-asyncio>=0.2.0; extra == "docs"
Requires-Dist: towncrier<25,>=24; extra == "docs"
Provides-Extra: eth
Requires-Dist: cached-property>=1.5.1; extra == "eth"
Requires-Dist: eth-bloom>=1.0.3; extra == "eth"
Requires-Dist: eth-keys>=0.4.0; extra == "eth"
Requires-Dist: eth-typing>=5.2.0; extra == "eth"
Requires-Dist: eth-utils>=2.0.0; extra == "eth"
Requires-Dist: lru-dict>=1.1.6; extra == "eth"
Requires-Dist: py-ecc>=8.0.0; extra == "eth"
Requires-Dist: rlp>=3.0.0; extra == "eth"
Requires-Dist: trie>=2.0.0; extra == "eth"
Requires-Dist: ckzg>=2.0.0; extra == "eth"
Provides-Extra: eth-extra
Requires-Dist: blake2b-py>=0.2.0; extra == "eth-extra"
Requires-Dist: coincurve>=18.0.0; extra == "eth-extra"
Provides-Extra: test
Requires-Dist: factory-boy>=3.0.0; extra == "test"
Requires-Dist: hypothesis<7,>=6; extra == "test"
Requires-Dist: pytest>=7.0.0; extra == "test"
Requires-Dist: pytest-asyncio>=0.20.0; extra == "test"
Requires-Dist: pytest-cov>=4.0.0; extra == "test"
Requires-Dist: pytest-timeout>=2.0.0; extra == "test"
Requires-Dist: pytest-xdist>=3.0; extra == "test"
Dynamic: author
Dynamic: author-email
Dynamic: classifier
Dynamic: description
Dynamic: description-content-type
Dynamic: home-page
Dynamic: keywords
Dynamic: license
Dynamic: license-file
Dynamic: provides-extra
Dynamic: requires-dist
Dynamic: requires-python
Dynamic: summary
